nessai_models/__init__.py
nessai_models/base.py
nessai_models/brewer.py
nessai_models/eggbox.py
nessai_models/gaussian.py
nessai_models/gaussianmixture.py
nessai_models/halfgaussian.py
nessai_models/mixture.py
nessai_models/pyramid.py
nessai_models/rosenbrock.py
nessai_models/signals.py
nessai_models/slabspike.py
nessai_models-0.5.0.dist-info/METADATA
nessai_models-0.5.0.dist-info/WHEEL
nessai_models-0.5.0.dist-info/top_level.txt
nessai_models-0.5.0.dist-info/RECORD
