Metadata-Version: 2.1
Name: nessai-models
Version: 0.5.0
Summary: Models for nessai
Author-email: "Michael J. Williams" <michaeljw1@googlemail.com>
License: MIT
Project-URL: Homepage, https://github.com/mj-will/nessai-models
Keywords: nested sampling,normalizing flows,machine learning,nessai
Classifier: Programming Language :: Python :: 3
Classifier: License :: OSI Approved :: MIT License
Classifier: Operating System :: OS Independent
Requires-Python: >=3.8
Requires-Dist: numpy >=1.9
Requires-Dist: scipy >0.16
Requires-Dist: nessai >=0.8.0
Provides-Extra: dev
Requires-Dist: black >=24.0 ; extra == 'dev'
Requires-Dist: flake8 ; extra == 'dev'
Requires-Dist: pre-commit ; extra == 'dev'
Requires-Dist: pytest >=6.0 ; extra == 'dev'
Requires-Dist: pytest-cov ; extra == 'dev'
Requires-Dist: pytest-integration ; extra == 'dev'
